CipherLib/__init__.py
CipherLib/audiostegano.py
CipherLib/encryption.py
CipherLib/passgen.py
CipherLib/stegano.py
Cred/__init__.py
Cred/__main__.py
Steg/__init__.py
Steg/__main__.py
StegCipher_Tools-0.13.0.dist-info/LICENSE.txt
StegCipher_Tools-0.13.0.dist-info/METADATA
StegCipher_Tools-0.13.0.dist-info/WHEEL
StegCipher_Tools-0.13.0.dist-info/entry_points.txt
StegCipher_Tools-0.13.0.dist-info/top_level.txt
StegCipher_Tools-0.13.0.dist-info/RECORD
