Metadata-Version: 2.1
Name: StegCipher-Tools
Version: 0.13.0
Summary: Collection of lib and GUI tool for steganography/manage/encrypt/decrypt your credentials.
Home-page: https://github.com/samsepiol-e/cipher
Author: Sam Sepiol
Author-email: 0.alicegawa@gmail.com
License: MIT
Platform: UNKNOWN
Classifier: License :: OSI Approved :: MIT License
Classifier: Programming Language :: Python
Classifier: Programming Language :: Python :: 3
Requires-Dist: pybase64
Requires-Dist: pycryptodome
Requires-Dist: pillow
Requires-Dist: pyperclip
Requires-Dist: ttkthemes
